dalle_mini/__init__.py
dalle_mini/data.py
dalle_mini/model/__init__.py
dalle_mini/model/configuration.py
dalle_mini/model/modeling.py
dalle_mini/model/partitions.py
dalle_mini/model/processor.py
dalle_mini/model/text.py
dalle_mini/model/tokenizer.py
dalle_mini/model/utils.py
dalle_mini-0.1.5.dist-info/LICENSE
dalle_mini-0.1.5.dist-info/METADATA
dalle_mini-0.1.5.dist-info/WHEEL
dalle_mini-0.1.5.dist-info/top_level.txt
dalle_mini-0.1.5.dist-info/RECORD
