Metadata-Version: 2.1
Name: dalle-mini
Version: 0.1.5
Summary: DALL·E mini - Generate images from a text prompt
Home-page: https://github.com/borisdayma/dalle-mini
Author: Boris Dayma et al.
Author-email: boris.dayma@gmail.com
Project-URL: Bug Tracker, https://github.com/borisdayma/dalle-mini/issues
Classifier: Programming Language :: Python :: 3
Classifier: License :: OSI Approved :: Apache Software License
Classifier: Operating System :: OS Independent
Classifier: Topic :: Scientific/Engineering :: Artificial Intelligence
Classifier: Development Status :: 3 - Alpha
Classifier: Intended Audience :: Developers
Requires-Python: >=3.6
License-File: LICENSE
Requires-Dist: transformers ==4.25.1
Requires-Dist: einops
Requires-Dist: unidecode
Requires-Dist: ftfy
Requires-Dist: emoji
Requires-Dist: pillow
Requires-Dist: jax ==0.3.25
Requires-Dist: flax ==0.6.3
Requires-Dist: orbax ==0.0.23
Requires-Dist: wandb
Provides-Extra: dev
Requires-Dist: tqdm ; extra == 'dev'
Requires-Dist: optax ; extra == 'dev'
Requires-Dist: braceexpand ; extra == 'dev'
Requires-Dist: datasets[streaming] ; extra == 'dev'
Requires-Dist: black[jupyter] ; extra == 'dev'
Requires-Dist: isort ; extra == 'dev'
